{
	"identifier": "B008",
	"uniqueIdentifer": "bd2803a0-8990-11ee-879a-35e5c16ba984",
	"x": 0,
	"y": 960,
	"width": 192,
	"height": 128,
	"bgColor": "#696A79",
	"neighbourLevels": [],
	"customFields" : {},
	"layers": [],
	"entities": {
		"Player_start_position": [
			{
				"id": "Player_start_position",
				"iid": "3c115540-8990-11ee-879a-e1300532f95f",
				"layer": "Special",
				"x": 32,
				"y": 80,
				"width": 16,
				"height": 16,
				"color": 15251350,
				"customFields": {
					"Direction": "Down"
				}
			}
		],
		"Boulder": [
			{
				"id": "Boulder",
				"iid": "2ba08050-8990-11ee-879a-b1be08dc948e",
				"layer": "Up",
				"x": 16,
				"y": 48,
				"width": 16,
				"height": 16,
				"color": 1578021,
				"customFields" : {}
			},
			{
				"id": "Boulder",
				"iid": "2be52a70-8990-11ee-879a-ddfbadb74d77",
				"layer": "Up",
				"x": 32,
				"y": 48,
				"width": 16,
				"height": 16,
				"color": 1578021,
				"customFields" : {}
			},
			{
				"id": "Boulder",
				"iid": "2c2c4590-8990-11ee-879a-3527e1d1b853",
				"layer": "Up",
				"x": 48,
				"y": 48,
				"width": 16,
				"height": 16,
				"color": 1578021,
				"customFields" : {}
			},
			{
				"id": "Boulder",
				"iid": "2d5ada80-8990-11ee-879a-6155779303e2",
				"layer": "Up",
				"x": 144,
				"y": 64,
				"width": 16,
				"height": 16,
				"color": 1578021,
				"customFields" : {}
			},
			{
				"id": "Boulder",
				"iid": "2d9e4c20-8990-11ee-879a-a94d9b6ad800",
				"layer": "Up",
				"x": 128,
				"y": 64,
				"width": 16,
				"height": 16,
				"color": 1578021,
				"customFields" : {}
			},
			{
				"id": "Boulder",
				"iid": "2e78f4b0-8990-11ee-879a-cfa8d61f7065",
				"layer": "Up",
				"x": 128,
				"y": 96,
				"width": 16,
				"height": 16,
				"color": 1578021,
				"customFields" : {}
			},
			{
				"id": "Boulder",
				"iid": "2ec91080-8990-11ee-879a-313af71c6a40",
				"layer": "Up",
				"x": 144,
				"y": 96,
				"width": 16,
				"height": 16,
				"color": 1578021,
				"customFields" : {}
			}
		],
		"Wall": [
			{
				"id": "Wall",
				"iid": "ec602df0-8990-11ee-879a-d3162086e347",
				"layer": "Ground",
				"x": 0,
				"y": 16,
				"width": 16,
				"height": 16,
				"color": 12470831,
				"customFields" : {}
			},
			{
				"id": "Wall",
				"iid": "eca74910-8990-11ee-879a-ef5a896cf369",
				"layer": "Ground",
				"x": 16,
				"y": 16,
				"width": 16,
				"height": 16,
				"color": 12470831,
				"customFields" : {}
			},
			{
				"id": "Wall",
				"iid": "ece9a940-8990-11ee-879a-1757e7a5c7d5",
				"layer": "Ground",
				"x": 16,
				"y": 0,
				"width": 16,
				"height": 16,
				"color": 12470831,
				"customFields" : {}
			},
			{
				"id": "Wall",
				"iid": "ed5da0c0-8990-11ee-879a-8b083ec6b76f",
				"layer": "Ground",
				"x": 32,
				"y": 0,
				"width": 16,
				"height": 16,
				"color": 12470831,
				"customFields" : {}
			},
			{
				"id": "Wall",
				"iid": "ed93f300-8990-11ee-879a-5d86e3743fad",
				"layer": "Ground",
				"x": 48,
				"y": 0,
				"width": 16,
				"height": 16,
				"color": 12470831,
				"customFields" : {}
			},
			{
				"id": "Wall",
				"iid": "eddb3530-8990-11ee-879a-15b4487a6066",
				"layer": "Ground",
				"x": 48,
				"y": 16,
				"width": 16,
				"height": 16,
				"color": 12470831,
				"customFields" : {}
			},
			{
				"id": "Wall",
				"iid": "f3070f70-8990-11ee-879a-f9d333292860",
				"layer": "Ground",
				"x": 64,
				"y": 16,
				"width": 16,
				"height": 16,
				"color": 12470831,
				"customFields" : {}
			},
			{
				"id": "Wall",
				"iid": "f34d1920-8990-11ee-879a-4dcc7f52324a",
				"layer": "Ground",
				"x": 80,
				"y": 16,
				"width": 16,
				"height": 16,
				"color": 12470831,
				"customFields" : {}
			},
			{
				"id": "Wall",
				"iid": "f3917520-8990-11ee-879a-598b0b619c53",
				"layer": "Ground",
				"x": 96,
				"y": 16,
				"width": 16,
				"height": 16,
				"color": 12470831,
				"customFields" : {}
			},
			{
				"id": "Wall",
				"iid": "f3d8b750-8990-11ee-879a-91cf50324b53",
				"layer": "Ground",
				"x": 112,
				"y": 16,
				"width": 16,
				"height": 16,
				"color": 12470831,
				"customFields" : {}
			},
			{
				"id": "Wall",
				"iid": "f465dc20-8990-11ee-879a-0f6bdd211393",
				"layer": "Ground",
				"x": 128,
				"y": 16,
				"width": 16,
				"height": 16,
				"color": 12470831,
				"customFields" : {}
			},
			{
				"id": "Wall",
				"iid": "f4ad1e50-8990-11ee-879a-e30c50ae4a02",
				"layer": "Ground",
				"x": 144,
				"y": 16,
				"width": 16,
				"height": 16,
				"color": 12470831,
				"customFields" : {}
			},
			{
				"id": "Wall",
				"iid": "f4f6d180-8990-11ee-879a-3bcb42518550",
				"layer": "Ground",
				"x": 160,
				"y": 16,
				"width": 16,
				"height": 16,
				"color": 12470831,
				"customFields" : {}
			},
			{
				"id": "Wall",
				"iid": "f7014780-8990-11ee-879a-c353d54426e4",
				"layer": "Ground",
				"x": 0,
				"y": 32,
				"width": 16,
				"height": 16,
				"color": 12470831,
				"customFields" : {}
			},
			{
				"id": "Wall",
				"iid": "f8bbefd0-8990-11ee-879a-af8c2af735b7",
				"layer": "Ground",
				"x": 0,
				"y": 48,
				"width": 16,
				"height": 16,
				"color": 12470831,
				"customFields" : {}
			},
			{
				"id": "Wall",
				"iid": "f8fe01e0-8990-11ee-879a-7b5b9b389941",
				"layer": "Ground",
				"x": 0,
				"y": 64,
				"width": 16,
				"height": 16,
				"color": 12470831,
				"customFields" : {}
			},
			{
				"id": "Wall",
				"iid": "f93edb70-8990-11ee-879a-55f9e1e6bc52",
				"layer": "Ground",
				"x": 0,
				"y": 80,
				"width": 16,
				"height": 16,
				"color": 12470831,
				"customFields" : {}
			},
			{
				"id": "Wall",
				"iid": "fb9af3e0-8990-11ee-879a-c76634d2d5dd",
				"layer": "Ground",
				"x": 0,
				"y": 96,
				"width": 16,
				"height": 16,
				"color": 12470831,
				"customFields" : {}
			},
			{
				"id": "Wall",
				"iid": "fbd6c460-8990-11ee-879a-15c0bfafd68b",
				"layer": "Ground",
				"x": 32,
				"y": 96,
				"width": 16,
				"height": 16,
				"color": 12470831,
				"customFields" : {}
			},
			{
				"id": "Wall",
				"iid": "fc1e0690-8990-11ee-879a-dfe0ae73d182",
				"layer": "Ground",
				"x": 16,
				"y": 96,
				"width": 16,
				"height": 16,
				"color": 12470831,
				"customFields" : {}
			},
			{
				"id": "Wall",
				"iid": "fd80a3d0-8990-11ee-879a-eff8a10ec827",
				"layer": "Ground",
				"x": 48,
				"y": 96,
				"width": 16,
				"height": 16,
				"color": 12470831,
				"customFields" : {}
			},
			{
				"id": "Wall",
				"iid": "fdbf0c60-8990-11ee-879a-050682b6e0ee",
				"layer": "Ground",
				"x": 64,
				"y": 96,
				"width": 16,
				"height": 16,
				"color": 12470831,
				"customFields" : {}
			},
			{
				"id": "Wall",
				"iid": "fe08bf90-8990-11ee-879a-81f9cfc7ae74",
				"layer": "Ground",
				"x": 64,
				"y": 80,
				"width": 16,
				"height": 16,
				"color": 12470831,
				"customFields" : {}
			},
			{
				"id": "Wall",
				"iid": "ffbcd830-8990-11ee-879a-0d289046d38c",
				"layer": "Ground",
				"x": 64,
				"y": 64,
				"width": 16,
				"height": 16,
				"color": 12470831,
				"customFields" : {}
			},
			{
				"id": "Wall",
				"iid": "fff637b0-8990-11ee-879a-fd4998f1dd99",
				"layer": "Ground",
				"x": 64,
				"y": 48,
				"width": 16,
				"height": 16,
				"color": 12470831,
				"customFields" : {}
			},
			{
				"id": "Wall",
				"iid": "01cf1660-8990-11ee-879a-6f90cab7fc4a",
				"layer": "Ground",
				"x": 80,
				"y": 48,
				"width": 16,
				"height": 16,
				"color": 12470831,
				"customFields" : {}
			},
			{
				"id": "Wall",
				"iid": "021260f0-8990-11ee-879a-8d72ae2468a8",
				"layer": "Ground",
				"x": 96,
				"y": 48,
				"width": 16,
				"height": 16,
				"color": 12470831,
				"customFields" : {}
			},
			{
				"id": "Wall",
				"iid": "02520200-8990-11ee-879a-bd9b35503d24",
				"layer": "Ground",
				"x": 112,
				"y": 48,
				"width": 16,
				"height": 16,
				"color": 12470831,
				"customFields" : {}
			},
			{
				"id": "Wall",
				"iid": "03af9630-8990-11ee-879a-158d3f12799b",
				"layer": "Ground",
				"x": 112,
				"y": 64,
				"width": 16,
				"height": 16,
				"color": 12470831,
				"customFields" : {}
			},
			{
				"id": "Wall",
				"iid": "05139300-8990-11ee-879a-4752f19cc40e",
				"layer": "Ground",
				"x": 96,
				"y": 64,
				"width": 16,
				"height": 16,
				"color": 12470831,
				"customFields" : {}
			},
			{
				"id": "Wall",
				"iid": "05535b20-8990-11ee-879a-999cbda169b1",
				"layer": "Ground",
				"x": 80,
				"y": 64,
				"width": 16,
				"height": 16,
				"color": 12470831,
				"customFields" : {}
			},
			{
				"id": "Wall",
				"iid": "05a34fe0-8990-11ee-879a-91389422c063",
				"layer": "Ground",
				"x": 96,
				"y": 80,
				"width": 16,
				"height": 16,
				"color": 12470831,
				"customFields" : {}
			},
			{
				"id": "Wall",
				"iid": "05eded70-8990-11ee-879a-654c6235a755",
				"layer": "Ground",
				"x": 96,
				"y": 96,
				"width": 16,
				"height": 16,
				"color": 12470831,
				"customFields" : {}
			},
			{
				"id": "Wall",
				"iid": "06f3ebc0-8990-11ee-879a-1fc16181cc6f",
				"layer": "Ground",
				"x": 80,
				"y": 96,
				"width": 16,
				"height": 16,
				"color": 12470831,
				"customFields" : {}
			},
			{
				"id": "Wall",
				"iid": "072bc4a0-8990-11ee-879a-45b7dff1aba4",
				"layer": "Ground",
				"x": 80,
				"y": 80,
				"width": 16,
				"height": 16,
				"color": 12470831,
				"customFields" : {}
			},
			{
				"id": "Wall",
				"iid": "0c01b6b0-8990-11ee-879a-67b59f78023f",
				"layer": "Ground",
				"x": 96,
				"y": 112,
				"width": 16,
				"height": 16,
				"color": 12470831,
				"customFields" : {}
			},
			{
				"id": "Wall",
				"iid": "0c4a3160-8990-11ee-879a-ab13a226fab8",
				"layer": "Ground",
				"x": 112,
				"y": 112,
				"width": 16,
				"height": 16,
				"color": 12470831,
				"customFields" : {}
			},
			{
				"id": "Wall",
				"iid": "0c9e1dc0-8990-11ee-879a-331c0ce7f5d8",
				"layer": "Ground",
				"x": 128,
				"y": 112,
				"width": 16,
				"height": 16,
				"color": 12470831,
				"customFields" : {}
			},
			{
				"id": "Wall",
				"iid": "0ceba180-8990-11ee-879a-553f374bff3b",
				"layer": "Ground",
				"x": 144,
				"y": 112,
				"width": 16,
				"height": 16,
				"color": 12470831,
				"customFields" : {}
			},
			{
				"id": "Wall",
				"iid": "0ed2d810-8990-11ee-879a-1d03c26bc50e",
				"layer": "Ground",
				"x": 176,
				"y": 48,
				"width": 16,
				"height": 16,
				"color": 12470831,
				"customFields" : {}
			},
			{
				"id": "Wall",
				"iid": "0f1b2bb0-8990-11ee-879a-65bb01ff38e8",
				"layer": "Ground",
				"x": 176,
				"y": 64,
				"width": 16,
				"height": 16,
				"color": 12470831,
				"customFields" : {}
			},
			{
				"id": "Wall",
				"iid": "11bbc730-8990-11ee-879a-63c60c6840f3",
				"layer": "Ground",
				"x": 176,
				"y": 80,
				"width": 16,
				"height": 16,
				"color": 12470831,
				"customFields" : {}
			},
			{
				"id": "Wall",
				"iid": "11fc52a0-8990-11ee-879a-f1457f25267d",
				"layer": "Ground",
				"x": 176,
				"y": 96,
				"width": 16,
				"height": 16,
				"color": 12470831,
				"customFields" : {}
			},
			{
				"id": "Wall",
				"iid": "123e8bc0-8990-11ee-879a-a7fc26834272",
				"layer": "Ground",
				"x": 176,
				"y": 112,
				"width": 16,
				"height": 16,
				"color": 12470831,
				"customFields" : {}
			},
			{
				"id": "Wall",
				"iid": "1285cdf0-8990-11ee-879a-e365f86fafc1",
				"layer": "Ground",
				"x": 160,
				"y": 112,
				"width": 16,
				"height": 16,
				"color": 12470831,
				"customFields" : {}
			},
			{
				"id": "Wall",
				"iid": "169785a0-8990-11ee-879a-abaaa440b1fd",
				"layer": "Ground",
				"x": 160,
				"y": 32,
				"width": 16,
				"height": 16,
				"color": 12470831,
				"customFields" : {}
			},
			{
				"id": "Wall",
				"iid": "170ed880-8990-11ee-879a-dbd7c16dab19",
				"layer": "Ground",
				"x": 176,
				"y": 32,
				"width": 16,
				"height": 16,
				"color": 12470831,
				"customFields" : {}
			}
		],
		"Hole": [
			{
				"id": "Hole",
				"iid": "2580d030-8990-11ee-879a-879185b0a3f9",
				"layer": "Ground",
				"x": 160,
				"y": 64,
				"width": 16,
				"height": 16,
				"color": 1578021,
				"customFields" : {}
			},
			{
				"id": "Hole",
				"iid": "25f5b210-8990-11ee-879a-b7cbaa8acafd",
				"layer": "Ground",
				"x": 112,
				"y": 80,
				"width": 16,
				"height": 16,
				"color": 1578021,
				"customFields" : {}
			},
			{
				"id": "Hole",
				"iid": "26723510-8990-11ee-879a-d1c4d312f2de",
				"layer": "Ground",
				"x": 160,
				"y": 96,
				"width": 16,
				"height": 16,
				"color": 1578021,
				"customFields" : {}
			},
			{
				"id": "Hole",
				"iid": "27c987b0-8990-11ee-879a-737d8d1a8ca6",
				"layer": "Ground",
				"x": 32,
				"y": 16,
				"width": 16,
				"height": 16,
				"color": 1578021,
				"customFields" : {}
			}
		],
		"Ground": [
			{
				"id": "Ground",
				"iid": "3215a370-8990-11ee-879a-411006575e51",
				"layer": "Ground",
				"x": 16,
				"y": 80,
				"width": 16,
				"height": 16,
				"color": 15251350,
				"customFields" : {}
			},
			{
				"id": "Ground",
				"iid": "325125d0-8990-11ee-879a-b1f5ea8f1638",
				"layer": "Ground",
				"x": 16,
				"y": 64,
				"width": 16,
				"height": 16,
				"color": 15251350,
				"customFields" : {}
			},
			{
				"id": "Ground",
				"iid": "328a5e40-8990-11ee-879a-3d1d33269cf9",
				"layer": "Ground",
				"x": 32,
				"y": 64,
				"width": 16,
				"height": 16,
				"color": 15251350,
				"customFields" : {}
			},
			{
				"id": "Ground",
				"iid": "32c4f640-8990-11ee-879a-f3e8fed22597",
				"layer": "Ground",
				"x": 32,
				"y": 80,
				"width": 16,
				"height": 16,
				"color": 15251350,
				"customFields" : {}
			},
			{
				"id": "Ground",
				"iid": "330fe1f0-8990-11ee-879a-a1935afafbe7",
				"layer": "Ground",
				"x": 48,
				"y": 64,
				"width": 16,
				"height": 16,
				"color": 15251350,
				"customFields" : {}
			},
			{
				"id": "Ground",
				"iid": "3351f400-8990-11ee-879a-911a36a32223",
				"layer": "Ground",
				"x": 48,
				"y": 80,
				"width": 16,
				"height": 16,
				"color": 15251350,
				"customFields" : {}
			},
			{
				"id": "Ground",
				"iid": "33cffda0-8990-11ee-879a-1506b5cccf94",
				"layer": "Ground",
				"x": 16,
				"y": 32,
				"width": 16,
				"height": 16,
				"color": 15251350,
				"customFields" : {}
			},
			{
				"id": "Ground",
				"iid": "3410d730-8990-11ee-879a-753e4210f3cf",
				"layer": "Ground",
				"x": 32,
				"y": 32,
				"width": 16,
				"height": 16,
				"color": 15251350,
				"customFields" : {}
			},
			{
				"id": "Ground",
				"iid": "344f3fc0-8990-11ee-879a-aff8048505c3",
				"layer": "Ground",
				"x": 48,
				"y": 32,
				"width": 16,
				"height": 16,
				"color": 15251350,
				"customFields" : {}
			},
			{
				"id": "Ground",
				"iid": "34912ac0-8990-11ee-879a-4d52571d3f22",
				"layer": "Ground",
				"x": 64,
				"y": 32,
				"width": 16,
				"height": 16,
				"color": 15251350,
				"customFields" : {}
			},
			{
				"id": "Ground",
				"iid": "34dd9d10-8990-11ee-879a-db46b259f4ca",
				"layer": "Ground",
				"x": 80,
				"y": 32,
				"width": 16,
				"height": 16,
				"color": 15251350,
				"customFields" : {}
			},
			{
				"id": "Ground",
				"iid": "356a73c0-8990-11ee-879a-b9ff979a9dd4",
				"layer": "Ground",
				"x": 96,
				"y": 32,
				"width": 16,
				"height": 16,
				"color": 15251350,
				"customFields" : {}
			},
			{
				"id": "Ground",
				"iid": "35b07d70-8990-11ee-879a-77024d2c5c78",
				"layer": "Ground",
				"x": 112,
				"y": 32,
				"width": 16,
				"height": 16,
				"color": 15251350,
				"customFields" : {}
			},
			{
				"id": "Ground",
				"iid": "35f7bfa0-8990-11ee-879a-9574faf8ad97",
				"layer": "Ground",
				"x": 128,
				"y": 32,
				"width": 16,
				"height": 16,
				"color": 15251350,
				"customFields" : {}
			},
			{
				"id": "Ground",
				"iid": "368f1da0-8990-11ee-879a-29b5a49f2709",
				"layer": "Ground",
				"x": 144,
				"y": 32,
				"width": 16,
				"height": 16,
				"color": 15251350,
				"customFields" : {}
			},
			{
				"id": "Ground",
				"iid": "36d8a9c0-8990-11ee-879a-059f1707eef3",
				"layer": "Ground",
				"x": 128,
				"y": 48,
				"width": 16,
				"height": 16,
				"color": 15251350,
				"customFields" : {}
			},
			{
				"id": "Ground",
				"iid": "37173960-8990-11ee-879a-459493a96337",
				"layer": "Ground",
				"x": 144,
				"y": 48,
				"width": 16,
				"height": 16,
				"color": 15251350,
				"customFields" : {}
			},
			{
				"id": "Ground",
				"iid": "37622510-8990-11ee-879a-43beea537372",
				"layer": "Ground",
				"x": 160,
				"y": 48,
				"width": 16,
				"height": 16,
				"color": 15251350,
				"customFields" : {}
			},
			{
				"id": "Ground",
				"iid": "37e29fb0-8990-11ee-879a-f762c4602b12",
				"layer": "Ground",
				"x": 160,
				"y": 80,
				"width": 16,
				"height": 16,
				"color": 15251350,
				"customFields" : {}
			},
			{
				"id": "Ground",
				"iid": "382722c0-8990-11ee-879a-b129b286e4c9",
				"layer": "Ground",
				"x": 144,
				"y": 80,
				"width": 16,
				"height": 16,
				"color": 15251350,
				"customFields" : {}
			},
			{
				"id": "Ground",
				"iid": "393d9bd0-8990-11ee-879a-29223ac3594a",
				"layer": "Ground",
				"x": 112,
				"y": 96,
				"width": 16,
				"height": 16,
				"color": 15251350,
				"customFields" : {}
			},
			{
				"id": "Ground",
				"iid": "93d9fdf0-8990-11ee-9530-a9d89c774fa6",
				"layer": "Ground",
				"x": 48,
				"y": 48,
				"width": 16,
				"height": 16,
				"color": 15251350,
				"customFields" : {}
			},
			{
				"id": "Ground",
				"iid": "942b7950-8990-11ee-9530-09f0d1933ebd",
				"layer": "Ground",
				"x": 32,
				"y": 48,
				"width": 16,
				"height": 16,
				"color": 15251350,
				"customFields" : {}
			},
			{
				"id": "Ground",
				"iid": "94902e90-8990-11ee-9530-79b6cf2ac369",
				"layer": "Ground",
				"x": 16,
				"y": 48,
				"width": 16,
				"height": 16,
				"color": 15251350,
				"customFields" : {}
			},
			{
				"id": "Ground",
				"iid": "9714b690-8990-11ee-9530-afb7c8e07a74",
				"layer": "Ground",
				"x": 144,
				"y": 64,
				"width": 16,
				"height": 16,
				"color": 15251350,
				"customFields" : {}
			},
			{
				"id": "Ground",
				"iid": "9768a2f0-8990-11ee-9530-fb042a03c99a",
				"layer": "Ground",
				"x": 128,
				"y": 64,
				"width": 16,
				"height": 16,
				"color": 15251350,
				"customFields" : {}
			},
			{
				"id": "Ground",
				"iid": "98064280-8990-11ee-9530-151701645bc3",
				"layer": "Ground",
				"x": 128,
				"y": 96,
				"width": 16,
				"height": 16,
				"color": 15251350,
				"customFields" : {}
			},
			{
				"id": "Ground",
				"iid": "98565e50-8990-11ee-9530-935418ac12bf",
				"layer": "Ground",
				"x": 144,
				"y": 96,
				"width": 16,
				"height": 16,
				"color": 15251350,
				"customFields" : {}
			}
		],
		"Down_stairs": [
			{
				"id": "Down_stairs",
				"iid": "9f05f260-8990-11ee-9530-4d9adfb5827c",
				"layer": "Ground",
				"x": 128,
				"y": 80,
				"width": 16,
				"height": 16,
				"color": 15251350,
				"customFields" : {}
			}
		]
	}
}